ninja_import/__init__.py
ninja_import/ninja_import.py
ninja_import-1.0.1.dist-info/METADATA
ninja_import-1.0.1.dist-info/WHEEL
ninja_import-1.0.1.dist-info/licenses/LICENSE
ninja_import-1.0.1.dist-info/RECORD
