Metadata-Version: 2.4
Name: ninja_import
Version: 1.0.1
License-File: LICENSE
Requires-Python: >=3.9
Provides-Extra: dev
Requires-Dist: pytest; extra == 'dev'
